pycryptotools/__init__.py
pycryptotools/blocks.py
pycryptotools/composite.py
pycryptotools/constants.py
pycryptotools/deterministic.py
pycryptotools/english.txt
pycryptotools/keccak.py
pycryptotools/keystore.py
pycryptotools/main.py
pycryptotools/mnemonic.py
pycryptotools/py2specials.py
pycryptotools/py3specials.py
pycryptotools/ripemd.py
pycryptotools/segwit_addr.py
pycryptotools/stealth.py
pycryptotools/transaction.py
pycryptotools/wallet.py
pycryptotools/wallet_utils.py
pycryptotools/coins/__init__.py
pycryptotools/coins/asset_type.py
pycryptotools/coins/base_coin.py
pycryptotools/coins/bitcoin.py
pycryptotools/coins/bitcoin_cash.py
pycryptotools/coins/counterparty.py
pycryptotools/coins/dash.py
pycryptotools/coins/dogecoin.py
pycryptotools/coins/ethereum.py
pycryptotools/coins/ethereum_forks.py
pycryptotools/coins/litecoin.py
pycryptotools/coins/unsupported_coin.py
pycryptotools/explorers/__init__.py
pycryptotools/explorers/base_explorer.py
pycryptotools/explorers/block_explorer.py
pycryptotools/explorers/blockscout_explorer.py
pycryptotools/explorers/blockstream_explorer.py
pycryptotools/explorers/bscscan.py
pycryptotools/explorers/coingate_price_explorer.py
pycryptotools/explorers/etherscan.py
pycryptotools/explorers/explorer_exceptions.py
pycryptotools/explorers/fullstack_explorer.py
pycryptotools/explorers/litecoinspace_explorer.py
pycryptotools/explorers/nft_explorer.py
pycryptotools/explorers/opensea.py
pycryptotools/explorers/price_explorer.py
pycryptotools/explorers/rarible.py
pycryptotools/explorers/sochain.py
pycryptotools/explorers/tokenscan_block_explorer.py
pycryptotools-0.3.2.data/scripts/cryptotool
pycryptotools-0.3.2.dist-info/LICENSE
pycryptotools-0.3.2.dist-info/METADATA
pycryptotools-0.3.2.dist-info/WHEEL
pycryptotools-0.3.2.dist-info/top_level.txt
pycryptotools-0.3.2.dist-info/RECORD
