Metadata-Version: 2.1
Name: pycryptotools
Version: 0.3.2
Summary: Python Crypto Coin Tools
Home-page: https://github.com/Toporin/pycryptotools
Author: Toporin
Author-email: satochip.wallet@gmail.com
Project-URL: Github, https://github.com/Toporin
Project-URL: Webshop, https://satochip.io/
Project-URL: Telegram, https://t.me/Satochip
Project-URL: Twitter, https://twitter.com/satochip
Project-URL: Source, https://github.com/Toporin/pycryptotools
Project-URL: Tracker, https://github.com/Toporin/pycryptotools/issues
Classifier: Development Status :: 5 - Production/Stable
Classifier: Intended Audience :: Developers
Classifier: Intended Audience :: Education
Classifier: License :: OSI Approved :: MIT License
Classifier: Operating System :: OS Independent
Classifier: Programming Language :: Python
Classifier: Programming Language :: Python :: 3
Classifier: Topic :: Security :: Cryptography
Requires-Python: >=3.6
License-File: LICENSE
Requires-Dist: base58 ~=2.1.1
Requires-Dist: cashaddress ~=1.0.6
Requires-Dist: pbkdf2 ~=1.3
Requires-Dist: requests ~=2.32.3
